framesvg/__init__.py
framesvg/py.typed
framesvg-0.3.0.dist-info/METADATA
framesvg-0.3.0.dist-info/WHEEL
framesvg-0.3.0.dist-info/entry_points.txt
framesvg-0.3.0.dist-info/licenses/LICENSE
framesvg-0.3.0.dist-info/RECORD
