Metadata-Version: 2.4
Name: framesvg
Version: 0.3.0
Summary: Convert animated GIFs to animated SVGs.
Project-URL: Homepage, https://github.com/romelium/framesvg
Project-URL: Repository, https://github.com/romelium/framesvg.git
Project-URL: Issues, https://github.com/romelium/framesvg/issues
Author-email: Romelium <author@romelium.cc>
Maintainer-email: Romelium <maintainer@romelium.cc>
License: MIT
License-File: LICENSE
Keywords: animation,gif,image-processing,svg,vector,vtracer
Classifier: Development Status :: 4 - Beta
Classifier: Intended Audience :: Developers
Classifier: Intended Audience :: End Users/Desktop
Classifier: License :: OSI Approved :: MIT License
Classifier: Operating System :: OS Independent
Classifier: Programming Language :: Python :: 3
Classifier: Programming Language :: Python :: 3 :: Only
Classifier: Programming Language :: Python :: 3.8
Classifier: Programming Language :: Python :: 3.9
Classifier: Programming Language :: Python :: 3.10
Classifier: Programming Language :: Python :: 3.11
Classifier: Programming Language :: Python :: 3.12
Classifier: Programming Language :: Python :: 3.13
Classifier: Topic :: Multimedia :: Graphics :: Editors :: Vector-Based
Classifier: Topic :: Multimedia :: Graphics :: Graphics Conversion
Classifier: Topic :: Utilities
Requires-Python: >=3.8
Requires-Dist: pillow>=10.0.0
Requires-Dist: vtracer>=0.6.0
